{
  "spec_0001": {
    "id": "spec_0001",
    "title": "Core Todo Management Features",
    "description": "Essential todo functionality including CRUD operations, filtering, and persistence",
    "requirements": [
      "Create new todo items with title and description",
      "Mark todos as complete/incomplete",
      "Delete todo items",
      "Filter todos by status (all, active, completed)",
      "Edit existing todo items",
      "Persist data locally and sync with backend"
    ],
    "acceptance_criteria": [
      "Users can add todos with Enter key or button click",
      "Todo status changes are immediate and persistent",
      "Filter buttons work correctly",
      "Data survives browser refresh",
      "Responsive design works on mobile"
    ],
    "dependencies": [
      "React state management",
      "Local storage API",
      "CSS framework"
    ],
    "tech_stack": [
      "React",
      "JavaScript",
      "CSS/SCSS",
      "Local Storage",
      "REST API"
    ],
    "timeline": "1-2 weeks",
    "complexity": "medium",
    "priority": "high",
    "status": "draft",
    "analysis": {
      "clarity_score": 0.8717948717948718,
      "completeness_score": 0.0,
      "feasibility_score": 0.8200000000000001,
      "complexity_score": 0.5,
      "risk_assessment": {
        "scope_creep": 0.35,
        "technical_debt": 0.02564102564102564,
        "timeline_risk": 0.17999999999999994,
        "quality_risk": 0.1282051282051282
      },
      "recommendations": [
        "Add more implementation details and technical specifications",
        "Add more explicit requirements using 'must', 'should', 'shall' language"
      ],
      "confidence": 0.6
    },
    "created_at": "2025-11-13T18:05:37.577044",
    "updated_at": "2025-11-13T18:05:37.577052"
  }
}